keyring.py
security.py
storage.py
utils.py
pyKeyring-0.6.data/scripts/keyring.py
pyKeyring-0.6.dist-info/LICENSE
pyKeyring-0.6.dist-info/METADATA
pyKeyring-0.6.dist-info/WHEEL
pyKeyring-0.6.dist-info/top_level.txt
pyKeyring-0.6.dist-info/RECORD
