Metadata-Version: 2.1
Name: pyKeyring
Version: 0.6
Summary: A simple and secure tool to store passwords
Home-page: https://github.com/gabrielperes97/pyKeyring
Author: Gabriel Leopoldino
Author-email: gabrielperes97@gmail.com
License: MIT
Platform: UNKNOWN
Classifier: Development Status :: 3 - Alpha
Classifier: Intended Audience :: Developers
Classifier: Natural Language :: English
Classifier: Environment :: Console
Classifier: License :: OSI Approved :: MIT License
Classifier: Operating System :: POSIX
Classifier: Operating System :: Microsoft :: Windows
Classifier: Operating System :: MacOS :: MacOS X
Classifier: Programming Language :: Python :: 3
Classifier: Programming Language :: Python :: 3.6
Classifier: Programming Language :: Python :: 3.5
Classifier: Programming Language :: Python :: 3.4
Classifier: Topic :: Security
Classifier: Topic :: Security :: Cryptography
Classifier: Topic :: Utilities
License-File: LICENSE
Requires-Dist: tinydb (>=3.11.1)
Requires-Dist: cryptography (==3.3.2)
Requires-Dist: pyperclip (>=1.6.4)
Requires-Dist: bson (>=0.5.6)
